tests/__init__.py
tests/test_api_url_builder.py
tests/test_client.py
tests/test_connection.py
xcodestream/__init__.py
xcodestream/client.py
xcodestream/connection.py
xcodestream/url_api_builder.py
xcodestream-0.0.8.dist-info/LICENSE
xcodestream-0.0.8.dist-info/METADATA
xcodestream-0.0.8.dist-info/WHEEL
xcodestream-0.0.8.dist-info/top_level.txt
xcodestream-0.0.8.dist-info/RECORD
