Metadata-Version: 2.1
Name: xcodestream
Version: 0.0.8
Summary: Xtream code api python scraper
Home-page: https://github.com/fazzani/minds_epg
Author: Heni Fazzani
Author-email: heni.fazzani@gmail.com
License: UNKNOWN
Platform: UNKNOWN
Classifier: Programming Language :: Python :: 3
Classifier: License :: OSI Approved :: MIT License
Classifier: Operating System :: OS Independent
